{
  "id": "knowledge-base/git/git-branch",
  "title": "Git Branching",
  "description": "Branching is a powerful feature in Git that allows you to diverge from the main line of development and continue to work without affecting that main line. Here are some common commands to create and manage branches in Git.",
  "source": "@site/docs/knowledge-base/git/02-git-branch.md",
  "sourceDirName": "knowledge-base/git",
  "slug": "/knowledge-base/git/git-branch",
  "permalink": "/my-blog-template/docs/knowledge-base/git/git-branch",
  "draft": false,
  "unlisted": false,
  "editUrl": "https://github.com/ognjenmanojlovic/my-blog-template.git/docs/knowledge-base/git/02-git-branch.md",
  "tags": [],
  "version": "current",
  "sidebarPosition": 2,
  "frontMatter": {
    "id": "git-branch",
    "title": "Git Branching",
    "sidebar_label": "Git Branching"
  },
  "sidebar": "tutorialSidebar",
  "previous": {
    "title": "Lifecycle in Git",
    "permalink": "/my-blog-template/docs/knowledge-base/git/lifecycle-in-git"
  },
  "next": {
    "title": "Overview",
    "permalink": "/my-blog-template/docs/knowledge-base/Container/overview"
  }
}